balba/__init__.py
balba/balba.py
balba/builder.py
balba/cli.py
balba/driver.py
balba/explorer.py
balba/models.py
balba/templates/balba.css
balba/templates/board.html
balba/templates/index.html
balba/templates/layout.html
balba-0.4.1.dist-info/entry_points.txt
balba-0.4.1.dist-info/LICENSE
balba-0.4.1.dist-info/WHEEL
balba-0.4.1.dist-info/METADATA
balba-0.4.1.dist-info/RECORD
