Metadata-Version: 2.1
Name: balba
Version: 0.4.1
Summary: Automatically generate a website showcasing Kicad projects.
Author-email: Antonio <antonio@zoftko.com>
Requires-Python: >=3.9.0
Requires-Dist: click>=8.1
Requires-Dist: jinja2>=3.1
Requires-Dist: PyYAML>=6.0
Requires-Dist: Markdown>=3.4
Requires-Dist: lxml>=4.9
Requires-Dist: commitizen>=3.10 ; extra == "dev"
Requires-Dist: tox>=4.8 ; extra == "test"
Project-URL: Source, https://gitlab.com/zoftko/balba
Provides-Extra: dev
Provides-Extra: test
